viswas_ai/__init__.py
viswas_ai/core.py
viswas_ai-0.1.3.dist-info/licenses/LICENSE
viswas_ai-0.1.3.dist-info/METADATA
viswas_ai-0.1.3.dist-info/WHEEL
viswas_ai-0.1.3.dist-info/top_level.txt
viswas_ai-0.1.3.dist-info/RECORD
