Metadata-Version: 2.4
Name: viswas-ai
Version: 0.1.3
Summary: A simple AI helper library
Author: Viswas
License-File: LICENSE
Requires-Dist: requests
Dynamic: author
Dynamic: description
Dynamic: description-content-type
Dynamic: license-file
Dynamic: requires-dist
Dynamic: summary
